eloy/__init__.py
eloy/alignment.py
eloy/calibration.py
eloy/centroid.py
eloy/detection.py
eloy/eloy_version.py
eloy/flux.py
eloy/photometry.py
eloy/psf.py
eloy/utils.py
eloy/viz.py
eloy/ballet/__init__.py
eloy/ballet/model.py
eloy/ballet/training.py
eloy-0.0.11b0.dist-info/METADATA
eloy-0.0.11b0.dist-info/WHEEL
eloy-0.0.11b0.dist-info/licenses/LICENSE
eloy-0.0.11b0.dist-info/RECORD
